{
  "de": [
    "showingAllShifts",
    "showingCurrentMonthShifts",
    "addToHomeScreen",
    "addToHomeScreenTitle",
    "iPhoneInstructions",
    "openInSafari",
    "tapShareButton",
    "scrollAndTapAddToHomeScreen",
    "tapAddInTopRight",
    "androidInstructions",
    "openInChrome",
    "tapMenuIcon",
    "tapAddOnPopup",
    "close",
    "exportedReport",
    "dateLabel",
    "backupFileCreated",
    "festiveDays",
    "addFestiveDay",
    "currentMonth",
    "allShifts",
    "editShift",
    "deleteShift",
    "shiftUpdatedSuccessfully",
    "shiftDeletedSuccessfully",
    "addToHomeScreeniOS",
    "addToHomeScreenAndroid",
    "ok",
    "upcomingShifts",
    "noUpcomingShifts",
    "shiftNotes",
    "settingsSaved",
    "addRule",
    "saveRule",
    "changesSaved",
    "errorInvalidShiftId",
    "notImplemented",
    "featureNotImplemented"
  ],

  "es": [
    "noUpcomingShifts",
    "notImplemented",
    "featureNotImplemented"
  ],

  "fr": [
    "noUpcomingShifts",
    "notImplemented",
    "featureNotImplemented"
  ],

  "he": [
    "noUpcomingShifts",
    "notImplemented",
    "featureNotImplemented"
  ],

  "ru": [
    "noUpcomingShifts",
    "notImplemented",
    "featureNotImplemented"
  ]
}
